qoa4ml/__init__.py
qoa4ml/qoa_client.py
qoa4ml/collector/__init__.py
qoa4ml/collector/amqp_collector.py
qoa4ml/collector/base_collector.py
qoa4ml/collector/host_object.py
qoa4ml/collector/kafka_collector.py
qoa4ml/collector/socket_collector.py
qoa4ml/config/__init__.py
qoa4ml/config/configs.py
qoa4ml/connector/__init__.py
qoa4ml/connector/amqp_connector.py
qoa4ml/connector/base_connector.py
qoa4ml/connector/debug_connector.py
qoa4ml/connector/kafka_connector.py
qoa4ml/connector/mqtt_connector.py
qoa4ml/connector/prom_connector.py
qoa4ml/connector/socket_connector.py
qoa4ml/lang/__init__.py
qoa4ml/lang/attributes.py
qoa4ml/lang/common_models.py
qoa4ml/lang/datamodel_enum.py
qoa4ml/lang/ml_contract.py
qoa4ml/observability/__init__.py
qoa4ml/observability/odop_obs/__init__.py
qoa4ml/observability/odop_obs/embedded_database.py
qoa4ml/observability/odop_obs/exporter.py
qoa4ml/observability/odop_obs/node_aggregator.py
qoa4ml/observability/odop_obs/example_config/exporter_config.yaml
qoa4ml/observability/odop_obs/example_config/node_aggregator_config.yaml
qoa4ml/observability/odop_obs/example_config/process_probe_conf.yaml
qoa4ml/observability/odop_obs/example_config/system_probe_conf.yaml
qoa4ml/observability/odop_obs/example_config/unit_conversion.yaml
qoa4ml/probes/__init__.py
qoa4ml/probes/docker_monitoring_probe.py
qoa4ml/probes/mlquality.py
qoa4ml/probes/probe.py
qoa4ml/probes/process_monitoring_probe.py
qoa4ml/probes/system_monitoring_probe.py
qoa4ml/reports/__init__.py
qoa4ml/reports/abstract_report.py
qoa4ml/reports/general_application_report.py
qoa4ml/reports/ml_report_model.py
qoa4ml/reports/ml_reports.py
qoa4ml/reports/resources_report_model.py
qoa4ml/reports/rohe_reports.py
qoa4ml/utils/__init__.py
qoa4ml/utils/dataquality_utils.py
qoa4ml/utils/docker_util.py
qoa4ml/utils/gpu_utils.py
qoa4ml/utils/jetson_utils.py
qoa4ml/utils/logger.py
qoa4ml/utils/pynvml_forked.py
qoa4ml/utils/qoa_utils.py
qoa4ml/utils/repeated_timer.py
qoa4ml-0.3.18.dist-info/METADATA
qoa4ml-0.3.18.dist-info/WHEEL
qoa4ml-0.3.18.dist-info/licenses/LICENSE
qoa4ml-0.3.18.dist-info/licenses/LICENSE.txt
qoa4ml-0.3.18.dist-info/RECORD
