Metadata-Version: 2.3
Name: qoa4ml
Version: 0.3.18
Summary: Quality of Analysis for Machine Learning
Project-URL: Repository, https://github.com/rdsea/QoA4ML
Project-URL: Documentation, https://rdsea.github.io/QoA4ML/
Project-URL: AaltoSEA, https://rdsea.github.io/
Author-email: AaltoSEA <tri.m.nguyen@aalto.fi>, nguu0123 <nguu0123@gmail.com>
License: Apache-2.0
Keywords: Machine Learning,Monitoring
Classifier: Development Status :: 3 - Alpha
Classifier: License :: OSI Approved :: Apache Software License
Classifier: Operating System :: POSIX :: Linux
Classifier: Programming Language :: Python :: 3.9
Classifier: Programming Language :: Python :: 3.10
Classifier: Programming Language :: Python :: 3.11
Classifier: Programming Language :: Python :: 3.12
Classifier: Topic :: Software Development :: Libraries
Classifier: Topic :: Software Development :: Libraries :: Python Modules
Classifier: Topic :: System :: Monitoring
Classifier: Topic :: Utilities
Requires-Python: >=3.9
Requires-Dist: devtools
Requires-Dist: docker==7.1.0
Requires-Dist: eval-type-backport>=0.2.0
Requires-Dist: fastapi>=0.110.2
Requires-Dist: flatten-dict>=0.4.2
Requires-Dist: lazy-import>=0.2.2
Requires-Dist: numpy>=1.23.5
Requires-Dist: pika>=1.3.2
Requires-Dist: psutil>=5.9.2
Requires-Dist: pydantic<2.8,>=2.7.4
Requires-Dist: pyyaml>=6.0.1
Requires-Dist: requests>=2.31.0
Requires-Dist: tinyflux>=1.0.0
Requires-Dist: uvicorn>=0.29.0
Provides-Extra: docs
Requires-Dist: cairosvg; extra == 'docs'
Requires-Dist: mkdocs-gen-files; extra == 'docs'
Requires-Dist: mkdocs-literate-nav; extra == 'docs'
Requires-Dist: mkdocs-material[imaging,recommended]>=9.5.17; extra == 'docs'
Requires-Dist: mkdocs-section-index; extra == 'docs'
Requires-Dist: mkdocstrings-python; extra == 'docs'
Provides-Extra: kafka
Requires-Dist: confluent-kafka>=2.4.0; extra == 'kafka'
Provides-Extra: ml
Requires-Dist: paho-mqtt==1.6.1; extra == 'ml'
Requires-Dist: pandas>=2.2.2; extra == 'ml'
Requires-Dist: pillow>=10.0.0; extra == 'ml'
Requires-Dist: prometheus-client==0.16.0; extra == 'ml'
Requires-Dist: tensorflow>=2.15.0; extra == 'ml'
Provides-Extra: otel
Requires-Dist: opentelemetry-api>=1.26.0; extra == 'otel'
Requires-Dist: opentelemetry-instrumentation-system-metrics>=0.47b0; extra == 'otel'
Requires-Dist: opentelemetry-sdk>=1.26.0; extra == 'otel'
